Quick_Sort_IC/counter.v
module counter(clk, reset, count);
    input clk, reset;
    output reg [4:0] count;

    always @ (posedge clk)
    begin
    //$display("reset = %d", reset);
        if(reset == 1) count = 0;
        else count = count + 1;
    end 

endmodule

Quick_Sort_IC/counter_test.v
`timescale 1ns / 1ps

module counter_test;
    reg clk, reset;
    wire [4:0] count;

    counter uut(.clk(clk), .reset(reset), .count(count));

    initial
    begin
        clk = 0;
        reset = 1;
        #100 reset = 0;
    end

    initial repeat (300) #40 clk = ~clk;

    initial $monitor("count = %d", count);

    initial
        begin
            $dumpfile ("count.vcd");
            $dumpvars (0, counter_test);
            #3000 $finish;
        end  

endmodule

Quick_Sort_IC/count.vcd
$date
	Thu Aug 15 22:37:15 2019
$end
$version
	Icarus Verilog
$end
$timescale
	1ps
$end
$scope module counter_test $end
$var wire 5 ! count [4:0] $end
$var reg 1 " clk $end
$var reg 1 # reset $end
$scope module uut $end
$var wire 1 " clk $end
$var wire 1 # reset $end
$var reg 5 $ count [4:0] $end
$upscope $end
$upscope $end
$enddefinitions $end
#0
$dumpvars
bx $
1#
0"
bx !
$end
#40000
b0 !
b0 $
1"
#80000
0"
#100000
0#
#120000
b1 !
b1 $
1"
#160000
0"
#200000
b10 !
b10 $
1"
#240000
0"
#280000
b11 !
b11 $
1"
#320000
0"
#360000
b100 !
b100 $
1"
#400000
0"
#440000
b101 !
b101 $
1"
#480000
0"
#520000
b110 !
b110 $
1"
#560000
0"
#600000
b111 !
b111 $
1"
#640000
0"
#680000
b1000 !
b1000 $
1"
#720000
0"
#760000
b1001 !
b1001 $
1"
#800000
0"
#840000
b1010 !
b1010 $
1"
#880000
0"
#920000
b1011 !
b1011 $
1"
#960000
0"
#1000000
b1100 !
b1100 $
1"
#1040000
0"
#1080000
b1101 !
b1101 $
1"
#1120000
0"
#1160000
b1110 !
b1110 $
1"
#1200000
0"
#1240000
b1111 !
b1111 $
1"
#1280000
0"
#1320000
b10000 !
b10000 $
1"
#1360000
0"
#1400000
b10001 !
b10001 $
1"
#1440000
0"
#1480000
b10010 !
b10010 $
1"
#1520000
0"
#1560000
b10011 !
b10011 $
1"
#1600000
0"
#1640000
b10100 !
b10100 $
1"
#1680000
0"
#1720000
b10101 !
b10101 $
1"
#1760000
0"
#1800000
b10110 !
b10110 $
1"
#1840000
0"
#1880000
b10111 !
b10111 $
1"
#1920000
0"
#1960000
b11000 !
b11000 $
1"
#2000000
0"
#2040000
b11001 !
b11001 $
1"
#2080000
0"
#2120000
b11010 !
b11010 $
1"
#2160000
0"
#2200000
b11011 !
b11011 $
1"
#2240000
0"
#2280000
b11100 !
b11100 $
1"
#2320000
0"
#2360000
b11101 !
b11101 $
1"
#2400000
0"
#2440000
b11110 !
b11110 $
1"
#2480000
0"
#2520000
b11111 !
b11111 $
1"
#2560000
0"
#2600000
b0 !
b0 $
1"
#2640000
0"
#2680000
b1 !
b1 $
1"
#2720000
0"
#2760000
b10 !
b10 $
1"
#2800000
0"
#2840000
b11 !
b11 $
1"
#2880000
0"
#2920000
b100 !
b100 $
1"
#2960000
0"
#3000000
b101 !
b101 $
1"
