Quick_Sort_IC/quick_sort.v
`timescale 1ns / 1ps
module quick_sort(clk, A, lo, hi);
    parameter WORD_SIZE = 16;

    input [WORD_SIZE-1:0] A, lo, hi;
    input clk;

    
    reg [WORD_SIZE-1:0] stack[0:4095];
    reg [WORD_SIZE-1:0] REG [0:4095];
    reg [WORD_SIZE-1:0] lo_reg, hi_reg, pivot, temp, i, j;
    reg [WORD_SIZE-1:0] stack_pointer;
    reg flag;
    //initial
    always @ (posedge clk)
    begin
        if (flag==0) begin
            $display("intial");
            stack_pointer=0;
            stack_pointer = stack_pointer + 1;
            stack[stack_pointer] = lo;
            //$display("intial\n");

            stack_pointer = stack_pointer + 1;
            stack[stack_pointer] = hi;
            flag=1;
        end
    end        

    always @ (posedge clk)
    begin    
        if(stack_pointer > 0 && flag>0)
        begin
            //$display("sorter1");
            hi_reg = stack[stack_pointer];
            stack_pointer = stack_pointer - 1;
            lo_reg = stack[stack_pointer];
            stack_pointer = stack_pointer - 1;
            
            if(lo_reg<hi_reg)
            begin
                pivot = REG[A+hi_reg];
               //$display("pivot=%d ", pivot);
                i = lo_reg;
                //$display("i=%d ", i);
                for (j=lo_reg; j<hi_reg; j=j+1)
                begin
                    //$display("j=%d ", j);
                    if(REG[A+j]<pivot)
                    begin
                        //$display("swap1\n");
                        //$display("%d %d", REG[A+i], REG[A+j]);
                        temp = REG[A+i];
                        REG[A+i] = REG[A+j];
                        REG[A+j] = temp;
                        i=i+1;
                    end
                end
                //$display("swap2\n");
                //$display("%d %d", REG[A+i], REG[A+hi_reg]);
                temp = REG[A+i];
                REG[A+i] = REG[A+hi_reg];
                REG[A+hi_reg] = temp;
                if(i>lo_reg) begin
                stack_pointer = stack_pointer + 1;
                stack[stack_pointer] = lo_reg;
                stack_pointer = stack_pointer + 1;
                stack[stack_pointer] = i-1;
                end
                if(i<hi_reg) begin
                stack_pointer = stack_pointer + 1;
                stack[stack_pointer] = i+1;
                stack_pointer = stack_pointer + 1;
                stack[stack_pointer] = hi_reg;
                end
            end
        end     
    end
/*
    always @ (posedge clk)
    begin    
        if(stack_pointer > 0 && flag>0)
        begin
            $display("sorter2");
            hi_reg = stack[stack_pointer];
            stack_pointer = stack_pointer - 1;
            lo_reg = stack[stack_pointer];
            stack_pointer = stack_pointer - 1;
            
            if(lo_reg<hi_reg)
            begin
                pivot = REG[A+hi_reg];
                //$display("pivot=%d ", pivot);
                i = lo_reg;
               // $display("i=%d ", i);
                for (j=lo_reg; j<hi_reg; j=j+1)
                begin
                   // $display("j=%d ", j);
                    if(REG[A+j]<pivot)
                    begin
                        //$display("swap1\n");
                        //$display("%d %d", REG[A+i], REG[A+j]);
                        temp = REG[A+i];
                        REG[A+i] = REG[A+j];
                        REG[A+j] = temp;
                        i=i+1;
                    end
                end
                //$display("swap2\n");
                //$display("%d %d", REG[A+i], REG[A+hi_reg]);
                temp = REG[A+i];
                REG[A+i] = REG[A+hi_reg];
                REG[A+hi_reg] = temp;
                if(i>1) begin
                stack_pointer = stack_pointer + 1;
                stack[stack_pointer] = lo_reg;
                stack_pointer = stack_pointer + 1;
                stack[stack_pointer] = i-1;
                end
                if(i+lo_reg<hi_reg) begin
                stack_pointer = stack_pointer + 1;
                stack[stack_pointer] = i+1;
                stack_pointer = stack_pointer + 1;
                stack[stack_pointer] = hi_reg;
                end
            end
        end
    end
    always @ (posedge clk)
    begin
        if(stack_pointer > 0 && flag>0)
        begin
            $display("sorter3");
            hi_reg = stack[stack_pointer];
            stack_pointer = stack_pointer - 1;
            lo_reg = stack[stack_pointer];
            stack_pointer = stack_pointer - 1;
            
            if(lo_reg<hi_reg)
            begin
                pivot = REG[A+hi_reg];
                //$display("pivot=%d ", pivot);
                i = lo_reg;
               // $display("i=%d ", i);
                for (j=lo_reg; j<hi_reg; j=j+1)
                begin
                   // $display("j=%d ", j);
                    if(REG[A+j]<pivot)
                    begin
                        //$display("swap1\n");
                        //$display("%d %d", REG[A+i], REG[A+j]);
                        temp = REG[A+i];
                        REG[A+i] = REG[A+j];
                        REG[A+j] = temp;
                        i=i+1;
                    end
                end
                //$display("swap2\n");
                //$display("%d %d", REG[A+i], REG[A+hi_reg]);
                temp = REG[A+i];
                REG[A+i] = REG[A+hi_reg];
                REG[A+hi_reg] = temp;
                if(i>1) begin
                stack_pointer = stack_pointer + 1;
                stack[stack_pointer] = lo_reg;
                stack_pointer = stack_pointer + 1;
                stack[stack_pointer] = i-1;
                end
                if(i+lo_reg<hi_reg) begin
                stack_pointer = stack_pointer + 1;
                stack[stack_pointer] = i+1;
                stack_pointer = stack_pointer + 1;
                stack[stack_pointer] = hi_reg;
                end
            end
        end
    end*/
endmodule

Quick_Sort_IC/quick_sort_test.v
`timescale 1ns / 1ps

module quick_sort_test;
    parameter WORD_SIZE = 16;
    reg [WORD_SIZE-1:0] A, lo, hi;
    reg clk;
    quick_sort uut(.clk(clk), .A(A), .lo(lo), .hi(hi));

    initial begin
        #10
        uut.flag <= 0;
        uut.stack_pointer <= 0;
        uut.REG[0] <= 55;
        uut.REG[1] <= 8;
        uut.REG[2] <= 34;
        uut.REG[3] <= 6;
        uut.REG[4] <= 5;
        uut.REG[5] <= 22;
        uut.REG[6] <= 33;
        uut.REG[7] <= 2;
        uut.REG[8] <= 1;
        uut.REG[9] <= 13;

        #20 A = 0;
        lo = 0;
        hi = 9; 
    end
    initial 
    begin
    clk = 0;
    repeat (300) #40 clk = ~clk;
    end

    initial
    begin
        $monitor("time=%t %d %d %d %d %d %d %d %d %d %d temp=%d pivot=%d i=%d j=%d lo_reg=%d, hi_reg=%d stack_pointer=%d stack_lo_0=%d stack_hi_0=%d\n",$time, uut.REG[0], uut.REG[1], 
        uut.REG[2], uut.REG[3], uut.REG[4], uut.REG[5], uut.REG[6], uut.REG[7], uut.REG[8], uut.REG[9],  uut.temp, uut.pivot, uut.i, uut.j, uut.lo_reg, uut.hi_reg, uut.stack_pointer, uut.stack[1], uut.stack[2]);
    end 

    
    initial
        begin
            $dumpfile ("quick.vcd");
            $dumpvars (0, quick_sort_test);
            #3000 $finish;
        end
endmodule

Quick_Sort_IC/quick.vcd
$date
	Sun Aug 18 14:02:40 2019
$end
$version
	Icarus Verilog
$end
$timescale
	1ps
$end
$scope module quick_sort_test $end
$var reg 16 ! A [15:0] $end
$var reg 1 " clk $end
$var reg 16 # hi [15:0] $end
$var reg 16 $ lo [15:0] $end
$scope module uut $end
$var wire 16 % A [15:0] $end
$var wire 1 " clk $end
$var wire 16 & hi [15:0] $end
$var wire 16 ' lo [15:0] $end
$var reg 1 ( flag $end
$var reg 16 ) hi_reg [15:0] $end
$var reg 16 * i [15:0] $end
$var reg 16 + j [15:0] $end
$var reg 16 , lo_reg [15:0] $end
$var reg 16 - pivot [15:0] $end
$var reg 16 . stack_pointer [15:0] $end
$var reg 16 / temp [15:0] $end
$upscope $end
$upscope $end
$enddefinitions $end
#0
$dumpvars
bx /
bx .
bx -
bx ,
bx +
bx *
bx )
x(
bx '
bx &
bx %
bx $
bx #
0"
bx !
$end
#10000
b0 .
0(
#30000
b1001 #
b1001 &
b0 $
b0 '
b0 !
b0 %
#40000
1(
b10 .
1"
#80000
0"
#120000
b10110 /
b1001 +
b101 *
b1101 -
b0 ,
b100 .
b1001 )
1"
#160000
0"
#200000
b100001 /
b1001 +
b110 *
b10110 -
b110 ,
b100 .
1"
#240000
0"
#280000
b110111 /
b1001 +
b111 *
b100001 -
b111 ,
b100 .
1"
#320000
0"
#360000
b110111 /
b1001 +
b1001 *
b110111 -
b1000 ,
b100 .
1"
#400000
0"
#440000
b10 .
b1000 )
1"
#480000
0"
#520000
b1000 /
b100 +
b0 *
b1 -
b0 ,
b10 .
b100 )
1"
#560000
0"
#600000
b1000 /
b100 +
b100 *
b1000 -
b1 ,
b10 .
1"
#640000
0"
#680000
b110 /
b11 +
b1 *
b10 -
b10 .
b11 )
1"
#720000
0"
#760000
b110 /
b11 +
b11 *
b110 -
b10 ,
b10 .
1"
#800000
0"
#840000
b0 .
b10 )
1"
