Quick_Sort_IC/REG.v
module REG (clk, addr, out, in, READ_EN, WRITE_EN);
    parameter WORD_SIZE = 16;

    input [WORD_SIZE-1:0] addr, in;
    input READ_EN, WRITE_EN, clk;
    output reg [WORD_SIZE-1:0] out;

    reg [WORD_SIZE-1:0] REG_FILE [0:4095];

    always  @(negedge clk) 
    begin
        if (WRITE_EN==1) begin
        REG_FILE[addr] <= in;
        //$display("Write %d at %d", in, addr);
        end
        else if (READ_EN==1) begin
        out <= REG_FILE[addr];
        //$display("Read %d at %d", REG_FILE[addr], addr);
        end
    end

endmodule

Quick_Sort_IC/REG_test.v
`timescale 1ns / 1ps
module REG_test;
    parameter WORD_SIZE = 16;

    reg clk;
    reg [WORD_SIZE-1:0] reg_addr, reg_in;
    wire [WORD_SIZE-1:0] reg_out;
    reg WRITE_EN, READ_EN;
    REG reg_file(.clk(clk), .addr(reg_addr), .out(reg_out), .in(reg_in), .READ_EN(READ_EN), .WRITE_EN(WRITE_EN));
    initial begin
        clk=0;
        READ_EN =0;
        WRITE_EN =1;
        reg_addr = 0;
        reg_in = 23;
        #40 clk = ~clk;
        #40 clk = ~clk;
        READ_EN =0;
        WRITE_EN =1;
        reg_addr = 1;
        reg_in = 24;
        #40 clk = ~clk;
        #40 clk = ~clk;
        READ_EN =0;
        WRITE_EN =1;
        reg_addr = 2;
        reg_in = 25;
        #40 clk = ~clk;
        #40 clk = ~clk;
        READ_EN =1;
        WRITE_EN =0;
        reg_addr = 0;
        #40 clk = ~clk;
        #40 clk = ~clk;
        $display("reg_out %d", reg_out);
        READ_EN =1;
        WRITE_EN =0;
        reg_addr = 1;
        #40 clk = ~clk;
        #40 clk = ~clk;
        $display("reg_out %d", reg_out);
        READ_EN =1;
        WRITE_EN =0;
        reg_addr = 2;
        #40 clk = ~clk;
        #40 clk = ~clk;
        $display("reg_out %d", reg_out);

        
    end 

    initial
    begin
        $monitor("%d %d %d \n", reg_file.REG_FILE[0], reg_file.REG_FILE[1], 
        reg_file.REG_FILE[2]);
    end

    initial
        begin
            $dumpfile ("REG.vcd");
            $dumpvars (0, REG_test);
            #3000 $finish;
        end    
endmodule

Quick_Sort_IC/REG.vcd
$date
	Wed Aug 14 15:42:38 2019
$end
$version
	Icarus Verilog
$end
$timescale
	1ps
$end
$scope module REG_test $end
$var wire 16 ! reg_out [15:0] $end
$var reg 1 " READ_EN $end
$var reg 1 # WRITE_EN $end
$var reg 1 $ clk $end
$var reg 16 % reg_addr [15:0] $end
$var reg 16 & reg_in [15:0] $end
$scope module reg_file $end
$var wire 1 " READ_EN $end
$var wire 1 # WRITE_EN $end
$var wire 16 ' addr [15:0] $end
$var wire 1 $ clk $end
$var wire 16 ( in [15:0] $end
$var reg 16 ) out [15:0] $end
$upscope $end
$upscope $end
$enddefinitions $end
#0
$dumpvars
bx )
b10111 (
b0 '
b10111 &
b0 %
0$
1#
0"
bx !
$end
#40000
1$
#80000
b11000 &
b11000 (
b1 %
b1 '
0$
#120000
1$
#160000
b11001 &
b11001 (
b10 %
b10 '
0$
#200000
1$
#240000
b0 %
b0 '
0#
1"
0$
#280000
b10111 !
b10111 )
1$
#320000
b1 %
b1 '
0$
#360000
b11000 !
b11000 )
1$
#400000
b10 %
b10 '
0$
#440000
b11001 !
b11001 )
1$
