Quick_Sort_IC/stack.v
module stack(clk, reset, push_en, pop_en, data_in1, data_in2, data_out1, data_out2, stack_pointer);
    parameter WORD_SIZE = 16;
    input clk, reset, push_en, pop_en;
    input [WORD_SIZE-1:0] data_in1, data_in2;
    output reg [WORD_SIZE-1:0] data_out1, data_out2, stack_pointer;
    reg [WORD_SIZE-1:0] stack [0:4095];
    reg [2:0] push_state, pop_state;

    always@ (posedge reset) stack_pointer <= 0;
    always@ (posedge push_en) push_state <= 0;
    always@ (posedge pop_en) pop_state <= 0;

    always@ (negedge clk) 
    begin
        if(push_en == 1) 
        begin
            case (push_state)
            default: begin
                
            end
            0:      begin 
                        stack_pointer = stack_pointer + 1;
                        $display("sp %d", stack_pointer);
                        push_state = 1;
                    end  
            1:      begin 
                        stack[stack_pointer] = data_in1;
                        $display("push %d", stack[stack_pointer]);
                        push_state = 2;
                    end  
            2:      begin 
                        stack_pointer = stack_pointer + 1;
                        $display("sp %d", stack_pointer);
                        push_state = 3;
                    end  
            3:      begin 
                        stack[stack_pointer] = data_in2;
                        $display("push %d", stack[stack_pointer]);
                        push_state = 4;
                    end
            4:      begin

                    end
            endcase
        end                   
        else if (pop_en == 1) 
        begin

           case (pop_state)
                default: begin
                    
                end

                0:  begin    
                    data_out1 = stack[stack_pointer];
                    $display("pop %d", stack[stack_pointer]); 
                    pop_state = 1;
                    end

                1:  begin    
                    stack_pointer = stack_pointer - 1;
                    $display("sp %d", stack_pointer);
                    pop_state = 2;
                    end

                2:  begin  
                    data_out2 = stack[stack_pointer];
                    $display("pop %d", stack[stack_pointer]); 
                    pop_state = 3;
                    end

                3:  begin    
                    stack_pointer = stack_pointer - 1;
                    $display("sp %d", stack_pointer);
                    pop_state = 4;
                    end
                4:  begin
                    
                    end
           endcase            
        end    
    end

endmodule

Quick_Sort_IC/stack_test.v
`timescale 1ns / 1ps

module stack_test;
    parameter WORD_SIZE = 16;

    reg clk, reset, push_en, pop_en;
    reg [WORD_SIZE-1:0] data_in1, data_in2;
    wire [WORD_SIZE-1:0] data_out1, data_out2, stack_pointer;

    stack uut(.clk(clk), .reset(reset), .push_en(push_en), .pop_en(pop_en), .data_in1(data_in1), .data_in2(data_in2), .data_out1(data_out1), .data_out2(data_out2), .stack_pointer(stack_pointer));
    initial begin
        clk=0;
        #10 reset = 0;
        #10 reset = 1;
        #10 reset = 0;
        push_en = 1;
        pop_en = 0;
        data_in1 = 22;
        data_in2 = 23;
        repeat(8) #10 clk = ~clk;
        #10 push_en = 0;
        #10 push_en = 1;
        data_in1 = 24;
        data_in2 = 25;
        repeat(8) #10 clk = ~clk;
        #10 push_en = 0;
        #10 push_en = 1;
        data_in1 = 26;
        data_in2 = 27;
        repeat(8) #10 clk = ~clk;
        push_en = 0;
        pop_en = 1;
        repeat(8) #10 clk = ~clk;
        #10 pop_en = 0;
        #10 pop_en = 1;
        repeat(8) #10 clk = ~clk;
        #10 pop_en = 0;
        #10 pop_en = 1;
        repeat(8) #10 clk = ~clk;

        
    end 

    initial
    begin
        $monitor("data_out1 %d data_out2 %d", data_out1, data_out2);
    end

    initial
        begin
            $dumpfile ("stack.vcd");
            $dumpvars (0, stack_test);
            #30000 $finish;
        end    

endmodule

Quick_Sort_IC/stack.vcd
$date
	Wed Aug 14 22:56:33 2019
$end
$version
	Icarus Verilog
$end
$timescale
	1ps
$end
$scope module stack_test $end
$var wire 16 ! stack_pointer [15:0] $end
$var wire 16 " data_out2 [15:0] $end
$var wire 16 # data_out1 [15:0] $end
$var reg 1 $ clk $end
$var reg 16 % data_in1 [15:0] $end
$var reg 16 & data_in2 [15:0] $end
$var reg 1 ' pop_en $end
$var reg 1 ( push_en $end
$var reg 1 ) reset $end
$scope module uut $end
$var wire 1 $ clk $end
$var wire 16 * data_in1 [15:0] $end
$var wire 16 + data_in2 [15:0] $end
$var wire 1 ' pop_en $end
$var wire 1 ( push_en $end
$var wire 1 ) reset $end
$var reg 16 , data_out1 [15:0] $end
$var reg 16 - data_out2 [15:0] $end
$var reg 3 . pop_state [2:0] $end
$var reg 3 / push_state [2:0] $end
$var reg 16 0 stack_pointer [15:0] $end
$upscope $end
$upscope $end
$enddefinitions $end
#0
$dumpvars
bx 0
bx /
bx .
bx -
bx ,
bx +
bx *
x)
x(
x'
bx &
bx %
0$
bx #
bx "
bx !
$end
#10000
0)
#20000
b0 !
b0 0
1)
#30000
b0 /
b10111 &
b10111 +
b10110 %
b10110 *
0'
1(
0)
#40000
1$
#50000
b1 /
b1 !
b1 0
0$
#60000
1$
#70000
b10 /
0$
#80000
1$
#90000
b11 /
b10 !
b10 0
0$
#100000
1$
#110000
b100 /
0$
#120000
0(
#130000
b0 /
b11001 &
b11001 +
b11000 %
b11000 *
1(
#140000
1$
#150000
b1 /
b11 !
b11 0
0$
#160000
1$
#170000
b10 /
0$
#180000
1$
#190000
b11 /
b100 !
b100 0
0$
#200000
1$
#210000
b100 /
0$
#220000
0(
#230000
b0 /
b11011 &
b11011 +
b11010 %
b11010 *
1(
#240000
1$
#250000
b1 /
b101 !
b101 0
0$
#260000
1$
#270000
b10 /
0$
#280000
1$
#290000
b11 /
b110 !
b110 0
0$
#300000
1$
#310000
b0 .
1'
0(
0$
#320000
1$
#330000
b1 .
0$
#340000
1$
#350000
b10 .
b101 !
b101 0
0$
#360000
1$
#370000
b11 .
b11010 "
b11010 -
0$
#380000
1$
#390000
b100 .
b100 !
b100 0
0$
#400000
0'
#410000
b0 .
1'
#420000
1$
#430000
b1 .
b11001 #
b11001 ,
0$
#440000
1$
#450000
b10 .
b11 !
b11 0
0$
#460000
1$
#470000
b11 .
b11000 "
b11000 -
0$
#480000
1$
#490000
b100 .
b10 !
b10 0
0$
#500000
0'
#510000
b0 .
1'
#520000
1$
#530000
b1 .
b10111 #
b10111 ,
0$
#540000
1$
#550000
b10 .
b1 !
b1 0
0$
#560000
1$
#570000
b11 .
b10110 "
b10110 -
0$
#580000
1$
#590000
b100 .
b0 !
b0 0
0$
