Quick_Sort_IC/REG.v
module REG (clk, addr, out, in, READ_EN, WRITE_EN);
    parameter WORD_SIZE = 16;

    input [WORD_SIZE-1:0] addr, in;
    input READ_EN, WRITE_EN, clk;
    output reg [WORD_SIZE-1:0] out;

    reg [WORD_SIZE-1:0] REG_FILE [0:4095];

    always  @(negedge clk) 
    begin
        if (WRITE_EN==1) begin
        REG_FILE[addr] <= in;
        //$display("Write %d at %d", in, addr);
        end
        else if (READ_EN==1) begin
        out <= REG_FILE[addr];
        //$display("Read %d at %d", REG_FILE[addr], addr);
        end
    end

endmodule

Quick_Sort_IC/swap.v
module swap(clk, addr1, addr2, reg_addr, reg_out, reg_in, reg_READ_EN, reg_WRITE_EN, swap_en);
    parameter WORD_SIZE =16;
    input clk, swap_en;
    input [WORD_SIZE-1:0] addr1, addr2, reg_out;
    output reg [WORD_SIZE-1:0] reg_addr, reg_in;
    output reg reg_READ_EN, reg_WRITE_EN;
    reg [WORD_SIZE-1:0] temp1, temp2;
    reg [2:0] state;

    always @(posedge swap_en) state = 0;
    
    
    always @(posedge clk) 
    begin
        case (state)
            
            default :  
                begin
                reg_READ_EN = 1;
                reg_WRITE_EN = 0;
                reg_addr = addr1;
                //$display("default reg_addr=%d", reg_addr);
                state=1;
                end
            
            0:  
                begin
                reg_READ_EN = 1;
                reg_WRITE_EN = 0;
                reg_addr = addr1;
                
                //$display("state0 reg_addr=%d ", reg_addr);
                state =1;
                end
            1:  
                begin
                reg_addr = addr2;
                temp1 = reg_out;
                //$display("state1 reg_addr=%d temp1=%d", reg_addr, temp1);
                state =2;
                end    
            
            2: 
                begin
                reg_READ_EN = 0;
                reg_WRITE_EN = 1;
                reg_addr = addr1;
                temp2 = reg_out;
                reg_in = temp2;
                //$display("state2 reg_addr=%d temp2=%d", reg_addr, temp2);
                state=3;
                end
            3: 
                begin
                reg_addr = addr2;
                reg_in = temp1;
                //$display("state3 reg_addr=%d reg_in=%d", reg_addr, reg_in);
                state = 4;
                end
            4:
                begin
                    reg_WRITE_EN = 0;    
                end          

        endcase
    end
endmodule

Quick_Sort_IC/swap_test.v
`timescale 1ns / 1ps
module swap_test;
    parameter WORD_SIZE = 16;
    reg [WORD_SIZE-1:0] addr1, addr2;
    reg clk, swap_en;
    wire [WORD_SIZE-1:0] reg_addr, reg_out, reg_in;
    wire WRITE_EN, READ_EN;
    swap uut(.clk(clk), .addr1(addr1),  .addr2(addr2), .reg_addr(reg_addr), .reg_out(reg_out), .reg_in(reg_in), .reg_READ_EN(READ_EN), .reg_WRITE_EN(WRITE_EN), .swap_en(swap_en));
    REG reg_file(.clk(clk), .addr(reg_addr), .out(reg_out), .in(reg_in), .READ_EN(READ_EN), .WRITE_EN(WRITE_EN));
    initial begin
        addr1 <= 0;
        addr2 <= 3;
        
        reg_file.REG_FILE[0] <= 9;
        reg_file.REG_FILE[1] <= 8;
        reg_file.REG_FILE[2] <= 7;
        reg_file.REG_FILE[3] <= 6;
        reg_file.REG_FILE[4] <= 5;
        reg_file.REG_FILE[5] <= 3;
        reg_file.REG_FILE[6] <= 4;
        reg_file.REG_FILE[7] <= 2;
        reg_file.REG_FILE[8] <= 1;
        reg_file.REG_FILE[9] <= 13;
        #2000
        swap_en <= 1;
        addr1 <= 4;
        addr2 <= 7;


        
    end 

    initial
    begin
        $monitor("%d %d %d %d %d %d %d %d %d %d\n", reg_file.REG_FILE[0], reg_file.REG_FILE[1], 
        reg_file.REG_FILE[2], reg_file.REG_FILE[3], reg_file.REG_FILE[4], reg_file.REG_FILE[5], reg_file.REG_FILE[6], reg_file.REG_FILE[7], 
        reg_file.REG_FILE[8], reg_file.REG_FILE[9]);
    end

    initial 
    begin
    #100 clk = 0;
    repeat (300) #40 clk = ~clk;
    end
    initial
        begin
            $dumpfile ("swap.vcd");
            $dumpvars (0, swap_test);
            #3000 $finish;
        end    
endmodule

Quick_Sort_IC/swap.vcd
$date
	Wed Aug 14 16:32:04 2019
$end
$version
	Icarus Verilog
$end
$timescale
	1ps
$end
$scope module swap_test $end
$var wire 16 ! reg_out [15:0] $end
$var wire 16 " reg_in [15:0] $end
$var wire 16 # reg_addr [15:0] $end
$var wire 1 $ WRITE_EN $end
$var wire 1 % READ_EN $end
$var reg 16 & addr1 [15:0] $end
$var reg 16 ' addr2 [15:0] $end
$var reg 1 ( clk $end
$var reg 1 ) swap_en $end
$scope module reg_file $end
$var wire 1 ( clk $end
$var wire 16 * in [15:0] $end
$var wire 16 + addr [15:0] $end
$var wire 1 $ WRITE_EN $end
$var wire 1 % READ_EN $end
$var reg 16 , out [15:0] $end
$upscope $end
$scope module uut $end
$var wire 16 - addr1 [15:0] $end
$var wire 16 . addr2 [15:0] $end
$var wire 1 ( clk $end
$var wire 16 / reg_out [15:0] $end
$var wire 1 ) swap_en $end
$var reg 1 % reg_READ_EN $end
$var reg 1 $ reg_WRITE_EN $end
$var reg 16 0 reg_addr [15:0] $end
$var reg 16 1 reg_in [15:0] $end
$var reg 3 2 state [2:0] $end
$var reg 16 3 temp1 [15:0] $end
$var reg 16 4 temp2 [15:0] $end
$upscope $end
$upscope $end
$enddefinitions $end
#0
$dumpvars
bx 4
bx 3
bx 2
bx 1
bx 0
bx /
b11 .
b0 -
bx ,
bx +
bx *
x)
x(
b11 '
b0 &
x%
x$
bx #
bx "
bx !
$end
#100000
0(
#140000
b1 2
b0 #
b0 +
b0 0
0$
1%
1(
#180000
b1001 !
b1001 ,
b1001 /
0(
#220000
b10 2
b1001 3
b11 #
b11 +
b11 0
1(
#260000
b110 !
b110 ,
b110 /
0(
#300000
b11 2
b110 "
b110 *
b110 1
b110 4
b0 #
b0 +
b0 0
1$
0%
1(
#340000
0(
#380000
b100 2
b1001 "
b1001 *
b1001 1
b11 #
b11 +
b11 0
1(
#420000
0(
#460000
0$
1(
#500000
0(
#540000
1(
#580000
0(
#620000
1(
#660000
0(
#700000
1(
#740000
0(
#780000
1(
#820000
0(
#860000
1(
#900000
0(
#940000
1(
#980000
0(
#1020000
1(
#1060000
0(
#1100000
1(
#1140000
0(
#1180000
1(
#1220000
0(
#1260000
1(
#1300000
0(
#1340000
1(
#1380000
0(
#1420000
1(
#1460000
0(
#1500000
1(
#1540000
0(
#1580000
1(
#1620000
0(
#1660000
1(
#1700000
0(
#1740000
1(
#1780000
0(
#1820000
1(
#1860000
0(
#1900000
1(
#1940000
0(
#1980000
1(
#2000000
b0 2
b111 '
b111 .
b100 &
b100 -
1)
#2020000
0(
#2060000
b1 2
b100 #
b100 +
b100 0
1%
1(
#2100000
b101 !
b101 ,
b101 /
0(
#2140000
b10 2
b101 3
b111 #
b111 +
b111 0
1(
#2180000
b10 !
b10 ,
b10 /
0(
#2220000
b11 2
b10 "
b10 *
b10 1
b10 4
b100 #
b100 +
b100 0
1$
0%
1(
#2260000
0(
#2300000
b100 2
b101 "
b101 *
b101 1
b111 #
b111 +
b111 0
1(
#2340000
0(
#2380000
0$
1(
